{
  "Sectors": [
    {
      "SectorName": "Information Technology (IT)",
      "Verticals": [
        "Healthcare",
        "Banking, Financial Services, and Insurance (BFSI)",
        "Retail",
        "Manufacturing",
        "Education",
        "Government",
        "Transportation and Logistics",
        "Energy and Utilities",
        "Telecommunications",
        "Real Estate",
        "Media and Entertainment",
        "Legal",
        "Hospitality",
        "Professional Services",
        "Automotive",
        "Agriculture",
        "Pharmaceutical",
        "Food and Beverage",
        "Consumer Goods",
        "Travel",
        "Construction",
        "Non-Profit",
        "Aerospace and Defense"
      ],
      "Specializations": [
        "Accessibility Engineering",
        "Artificial Intelligence and Machine Learning",
        "Big Data Solutions",
        "Blockchain Development",
        "Cloud Architecture",
        "Cloud Computing and Cloud Services",
        "CRM Systems Implementation and Management",
        "Cybersecurity and Information Security",
        "Data Analysis and Business Intelligence",
        "Database Management and Administration",
        "DevOps",
        "Digital Marketing",
        "E-commerce Solutions",
        "Edge Computing",
        "Enterprise Resource Planning (ERP) Implementation",
        "Ethical Hacking and Penetration Testing",
        "Full Stack Development",
        "Game Development",
        "Geographic Information Systems (GIS)",
        "Health Informatics",
        "Human-Computer Interaction",
        "Internet of Things (IoT) Solutions",
        "IT Consultancy and Project Management",
        "IT Infrastructure and Systems Administration",
        "IT Service Management",
        "IT Strategy and Planning",
        "IT Support and Helpdesk Services",
        "IT Training and Education",
        "Mobile App Development",
        "Network Engineering and Administration",
        "Quantum Computing",
        "Regulatory Compliance",
        "Robotics Programming",
        "Software Architecture",
        "Software Development",
        "Software Maintenance",
        "Software Testing and Quality Assurance",
        "System Integration",
        "Technical Writing",
        "User Experience (UX) and User Interface (UI) Design",
        "Virtual Reality (VR) and Augmented Reality (AR) Development",
        "Web Development and Design"
      ],
      "ProgrammingLanguages": [
        "C",
        "C++",
        "Java",
        "Python",
        "C#",
        "JavaScript",
        "TypeScript",
        "PHP",
        "Ruby",
        "Swift",
        "Objective-C",
        "Kotlin",
        "Go",
        "Rust",
        "SQL",
        "R",
        "MATLAB",
        "Dart",
        "Perl",
        "Scala",
        "Lua",
        "Haskell",
        "Clojure",
        "Shell Scripting",
        "Groovy",
        "Erlang",
        "Elixir",
        "F#",
        "Assembly Language",
        "VB.NET",
        "Julia",
        "Ada",
        "Fortran",
        "COBOL",
        "Pascal",
        "Delphi",
        "Prolog",
        "Elm"
      ],
      "concepts": [
        "Variables and Data Types",
        "Control Structures ",
        "Functions and Methods",
        "Object-Oriented Programming (OOP)",
        "Functional Programming",
        "Error Handling and Exceptions",
        "Data Structures ",
        "Algorithms ",
        "Concurrency and Parallelism",
        "Memory Management",
        "Recursion",
        "Design Patterns",
        "Software Development Life Cycle (SDLC)",
        "Version Control Systems",
        "Testing (Unit, Integration, System)",
        "Debugging Techniques",
        "Database Management",
        "Network Programming",
        "API Design and Usage",
        "Security Practices"
      ],
      "ToolsTechnologiesPlatformsFrameworks": [
        "Git",
        "Docker",
        "Jenkins",
        "JIRA",
        "Selenium",
        "Ansible",
        "RESTful APIs",
        "Internet of Things (IoT)",
        "MySQL",
        "PostgreSQL",
        "MongoDB",
        "Redis",
        "Elasticsearch",
        "Oracle Database",
        "Microsoft SQL Server",
        "Cassandra",
        "SQLite",
        "AWS (Amazon Web Services)",
        "Microsoft Azure",
        "Google Cloud Platform",
        "Salesforce",
        "Heroku",
        "Kubernetes",
        "React",
        "Angular",
        "NET",
        "Node.js",
        "Spring Framework",
        "Django",
        "Flask",
        "Ruby on Rails",
        "Laravel",
        "Bootstrap",
        "TensorFlow",
        "Vue.js",
        "Ember.js",
        "Svelte",
        "Xamarin",
        "Apache Cordova",
        "Ionic"
      ]
    }
  ]
}
